VFO/__init__.py
VFO/optimizer.py
vfo_optimizer-0.1.0.dist-info/METADATA
vfo_optimizer-0.1.0.dist-info/WHEEL
vfo_optimizer-0.1.0.dist-info/top_level.txt
vfo_optimizer-0.1.0.dist-info/RECORD
