Metadata-Version: 2.4
Name: vfo-optimizer
Version: 0.1.0
Summary: Van Fish Optimization (VFO) Algorithm
Author: Emine AYAZ Ph.D.
Classifier: Programming Language :: Python :: 3
Classifier: License :: OSI Approved :: MIT License
Classifier: Operating System :: OS Independent
Requires-Python: >=3.6
Requires-Dist: numpy
Dynamic: author
Dynamic: classifier
Dynamic: description
Dynamic: description-content-type
Dynamic: requires-dist
Dynamic: requires-python
Dynamic: summary
